wp_socket/__init__.py
wp_socket/client.py
wp_socket-0.0.27.dist-info/LICENSE
wp_socket-0.0.27.dist-info/METADATA
wp_socket-0.0.27.dist-info/WHEEL
wp_socket-0.0.27.dist-info/top_level.txt
wp_socket-0.0.27.dist-info/RECORD
